magic_math.py
magic_maths-0.1.1.dist-info/LICENSE
magic_maths-0.1.1.dist-info/METADATA
magic_maths-0.1.1.dist-info/WHEEL
magic_maths-0.1.1.dist-info/top_level.txt
magic_maths-0.1.1.dist-info/RECORD
