Metadata-Version: 2.1
Name: magic-maths
Version: 0.1.1
Summary: magically import evaluated math expressions
Requires-Python: >=3.10
License-File: LICENSE
